<?xml version="1.0" encoding="UTF-8"?>
<!DOCTYPE result>
<result>
	<players>
		<player>
			<account_id>139514591</account_id>
			<player_slot>0</player_slot>
			<hero_id>60</hero_id>
			<item_0>50</item_0>
			<item_1>151</item_1>
			<item_2>30</item_2>
			<item_3>154</item_3>
			<item_4>41</item_4>
			<item_5>92</item_5>
			<kills>10</kills>
			<deaths>2</deaths>
			<assists>9</assists>
			<leaver_status>0</leaver_status>
			<gold>3045</gold>
			<last_hits>65</last_hits>
			<denies>3</denies>
			<gold_per_min>481</gold_per_min>
			<xp_per_min>447</xp_per_min>
			<gold_spent>11215</gold_spent>
			<hero_damage>14148</hero_damage>
			<tower_damage>5013</tower_damage>
			<hero_healing>161</hero_healing>
			<level>15</level>
			<ability_upgrades>
				<ability>
					<ability>5275</ability>
					<time>326</time>
					<level>1</level>
				</ability>
				<ability>
					<ability>5277</ability>
					<time>459</time>
					<level>2</level>
				</ability>
				<ability>
					<ability>5275</ability>
					<time>485</time>
					<level>3</level>
				</ability>
				<ability>
					<ability>5277</ability>
					<time>552</time>
					<level>4</level>
				</ability>
				<ability>
					<ability>5275</ability>
					<time>617</time>
					<level>5</level>
				</ability>
				<ability>
					<ability>5278</ability>
					<time>697</time>
					<level>6</level>
				</ability>
				<ability>
					<ability>5275</ability>
					<time>772</time>
					<level>7</level>
				</ability>
				<ability>
					<ability>5276</ability>
					<time>817</time>
					<level>8</level>
				</ability>
				<ability>
					<ability>5277</ability>
					<time>931</time>
					<level>9</level>
				</ability>
				<ability>
					<ability>5277</ability>
					<time>1139</time>
					<level>10</level>
				</ability>
				<ability>
					<ability>5278</ability>
					<time>1181</time>
					<level>11</level>
				</ability>
				<ability>
					<ability>5276</ability>
					<time>1455</time>
					<level>12</level>
				</ability>
				<ability>
					<ability>5276</ability>
					<time>1572</time>
					<level>13</level>
				</ability>
				<ability>
					<ability>5276</ability>
					<time>1879</time>
					<level>14</level>
				</ability>
				<ability>
					<ability>5002</ability>
					<time>2091</time>
					<level>15</level>
				</ability>
			</ability_upgrades>
		</player>
		<player>
			<account_id>181120280</account_id>
			<player_slot>1</player_slot>
			<hero_id>29</hero_id>
			<item_0>180</item_0>
			<item_1>1</item_1>
			<item_2>110</item_2>
			<item_3>36</item_3>
			<item_4>46</item_4>
			<item_5>58</item_5>
			<kills>6</kills>
			<deaths>0</deaths>
			<assists>12</assists>
			<leaver_status>0</leaver_status>
			<gold>96</gold>
			<last_hits>120</last_hits>
			<denies>11</denies>
			<gold_per_min>490</gold_per_min>
			<xp_per_min>414</xp_per_min>
			<gold_spent>16425</gold_spent>
			<hero_damage>8455</hero_damage>
			<tower_damage>1476</tower_damage>
			<hero_healing>0</hero_healing>
			<level>15</level>
			<ability_upgrades>
				<ability>
					<ability>5120</ability>
					<time>418</time>
					<level>1</level>
				</ability>
				<ability>
					<ability>5119</ability>
					<time>500</time>
					<level>2</level>
				</ability>
				<ability>
					<ability>5120</ability>
					<time>599</time>
					<level>3</level>
				</ability>
				<ability>
					<ability>5119</ability>
					<time>673</time>
					<level>4</level>
				</ability>
				<ability>
					<ability>5118</ability>
					<time>828</time>
					<level>5</level>
				</ability>
				<ability>
					<ability>5121</ability>
					<time>927</time>
					<level>6</level>
				</ability>
				<ability>
					<ability>5120</ability>
					<time>1068</time>
					<level>7</level>
				</ability>
				<ability>
					<ability>5120</ability>
					<time>1137</time>
					<level>8</level>
				</ability>
				<ability>
					<ability>5119</ability>
					<time>1332</time>
					<level>9</level>
				</ability>
				<ability>
					<ability>5119</ability>
					<time>1454</time>
					<level>10</level>
				</ability>
				<ability>
					<ability>5121</ability>
					<time>1525</time>
					<level>11</level>
				</ability>
				<ability>
					<ability>5118</ability>
					<time>1734</time>
					<level>12</level>
				</ability>
				<ability>
					<ability>5118</ability>
					<time>1798</time>
					<level>13</level>
				</ability>
				<ability>
					<ability>5118</ability>
					<time>2070</time>
					<level>14</level>
				</ability>
				<ability>
					<ability>5002</ability>
					<time>2137</time>
					<level>15</level>
				</ability>
			</ability_upgrades>
		</player>
		<player>
			<account_id>4294967295</account_id>
			<player_slot>2</player_slot>
			<hero_id>102</hero_id>
			<item_0>36</item_0>
			<item_1>180</item_1>
			<item_2>242</item_2>
			<item_3>0</item_3>
			<item_4>0</item_4>
			<item_5>0</item_5>
			<kills>3</kills>
			<deaths>3</deaths>
			<assists>12</assists>
			<leaver_status>0</leaver_status>
			<gold>2134</gold>
			<last_hits>41</last_hits>
			<denies>16</denies>
			<gold_per_min>331</gold_per_min>
			<xp_per_min>351</xp_per_min>
			<gold_spent>7410</gold_spent>
			<hero_damage>5615</hero_damage>
			<tower_damage>1056</tower_damage>
			<hero_healing>2314</hero_healing>
			<level>13</level>
			<ability_upgrades>
				<ability>
					<ability>5586</ability>
					<time>434</time>
					<level>1</level>
				</ability>
				<ability>
					<ability>5585</ability>
					<time>500</time>
					<level>2</level>
				</ability>
				<ability>
					<ability>5585</ability>
					<time>596</time>
					<level>3</level>
				</ability>
				<ability>
					<ability>5586</ability>
					<time>673</time>
					<level>4</level>
				</ability>
				<ability>
					<ability>5585</ability>
					<time>826</time>
					<level>5</level>
				</ability>
				<ability>
					<ability>5588</ability>
					<time>926</time>
					<level>6</level>
				</ability>
				<ability>
					<ability>5585</ability>
					<time>1038</time>
					<level>7</level>
				</ability>
				<ability>
					<ability>5586</ability>
					<time>1116</time>
					<level>8</level>
				</ability>
				<ability>
					<ability>5586</ability>
					<time>1334</time>
					<level>9</level>
				</ability>
				<ability>
					<ability>5587</ability>
					<time>1521</time>
					<level>10</level>
				</ability>
				<ability>
					<ability>5588</ability>
					<time>1581</time>
					<level>11</level>
				</ability>
				<ability>
					<ability>5587</ability>
					<time>1773</time>
					<level>12</level>
				</ability>
				<ability>
					<ability>5587</ability>
					<time>2013</time>
					<level>13</level>
				</ability>
			</ability_upgrades>
		</player>
		<player>
			<account_id>4294967295</account_id>
			<player_slot>3</player_slot>
			<hero_id>75</hero_id>
			<item_0>102</item_0>
			<item_1>34</item_1>
			<item_2>79</item_2>
			<item_3>43</item_3>
			<item_4>0</item_4>
			<item_5>29</item_5>
			<kills>3</kills>
			<deaths>1</deaths>
			<assists>10</assists>
			<leaver_status>0</leaver_status>
			<gold>2231</gold>
			<last_hits>21</last_hits>
			<denies>3</denies>
			<gold_per_min>284</gold_per_min>
			<xp_per_min>337</xp_per_min>
			<gold_spent>6525</gold_spent>
			<hero_damage>8745</hero_damage>
			<tower_damage>1664</tower_damage>
			<hero_healing>1418</hero_healing>
			<level>13</level>
			<ability_upgrades>
				<ability>
					<ability>5379</ability>
					<time>499</time>
					<level>1</level>
				</ability>
				<ability>
					<ability>5378</ability>
					<time>503</time>
					<level>2</level>
				</ability>
				<ability>
					<ability>5377</ability>
					<time>557</time>
					<level>3</level>
				</ability>
				<ability>
					<ability>5379</ability>
					<time>645</time>
					<level>4</level>
				</ability>
				<ability>
					<ability>5379</ability>
					<time>791</time>
					<level>5</level>
				</ability>
				<ability>
					<ability>5380</ability>
					<time>931</time>
					<level>6</level>
				</ability>
				<ability>
					<ability>5379</ability>
					<time>1087</time>
					<level>7</level>
				</ability>
				<ability>
					<ability>5377</ability>
					<time>1310</time>
					<level>8</level>
				</ability>
				<ability>
					<ability>5377</ability>
					<time>1455</time>
					<level>9</level>
				</ability>
				<ability>
					<ability>5377</ability>
					<time>1584</time>
					<level>10</level>
				</ability>
				<ability>
					<ability>5380</ability>
					<time>1649</time>
					<level>11</level>
				</ability>
				<ability>
					<ability>5378</ability>
					<time>2097</time>
					<level>12</level>
				</ability>
				<ability>
					<ability>5378</ability>
					<time>2122</time>
					<level>13</level>
				</ability>
			</ability_upgrades>
		</player>
		<player>
			<account_id>140400895</account_id>
			<player_slot>4</player_slot>
			<hero_id>93</hero_id>
			<item_0>185</item_0>
			<item_1>152</item_1>
			<item_2>36</item_2>
			<item_3>63</item_3>
			<item_4>0</item_4>
			<item_5>160</item_5>
			<kills>10</kills>
			<deaths>4</deaths>
			<assists>8</assists>
			<leaver_status>0</leaver_status>
			<gold>1395</gold>
			<last_hits>132</last_hits>
			<denies>11</denies>
			<gold_per_min>556</gold_per_min>
			<xp_per_min>399</xp_per_min>
			<gold_spent>13680</gold_spent>
			<hero_damage>11345</hero_damage>
			<tower_damage>3022</tower_damage>
			<hero_healing>0</hero_healing>
			<level>14</level>
			<ability_upgrades>
				<ability>
					<ability>5495</ability>
					<time>473</time>
					<level>1</level>
				</ability>
				<ability>
					<ability>5496</ability>
					<time>500</time>
					<level>2</level>
				</ability>
				<ability>
					<ability>5495</ability>
					<time>557</time>
					<level>3</level>
				</ability>
				<ability>
					<ability>5494</ability>
					<time>633</time>
					<level>4</level>
				</ability>
				<ability>
					<ability>5495</ability>
					<time>696</time>
					<level>5</level>
				</ability>
				<ability>
					<ability>5497</ability>
					<time>872</time>
					<level>6</level>
				</ability>
				<ability>
					<ability>5495</ability>
					<time>990</time>
					<level>7</level>
				</ability>
				<ability>
					<ability>5494</ability>
					<time>1130</time>
					<level>8</level>
				</ability>
				<ability>
					<ability>5494</ability>
					<time>1399</time>
					<level>9</level>
				</ability>
				<ability>
					<ability>5494</ability>
					<time>1530</time>
					<level>10</level>
				</ability>
				<ability>
					<ability>5497</ability>
					<time>1580</time>
					<level>11</level>
				</ability>
				<ability>
					<ability>5496</ability>
					<time>1790</time>
					<level>12</level>
				</ability>
				<ability>
					<ability>5496</ability>
					<time>1829</time>
					<level>13</level>
				</ability>
				<ability>
					<ability>5496</ability>
					<time>2056</time>
					<level>14</level>
				</ability>
			</ability_upgrades>
		</player>
		<player>
			<account_id>188998092</account_id>
			<player_slot>128</player_slot>
			<hero_id>44</hero_id>
			<item_0>50</item_0>
			<item_1>81</item_1>
			<item_2>151</item_2>
			<item_3>46</item_3>
			<item_4>0</item_4>
			<item_5>0</item_5>
			<kills>4</kills>
			<deaths>6</deaths>
			<assists>3</assists>
			<leaver_status>0</leaver_status>
			<gold>2234</gold>
			<last_hits>64</last_hits>
			<denies>1</denies>
			<gold_per_min>341</gold_per_min>
			<xp_per_min>362</xp_per_min>
			<gold_spent>7415</gold_spent>
			<hero_damage>4059</hero_damage>
			<tower_damage>0</tower_damage>
			<hero_healing>0</hero_healing>
			<level>14</level>
			<ability_upgrades>
				<ability>
					<ability>5190</ability>
					<time>326</time>
					<level>1</level>
				</ability>
				<ability>
					<ability>5191</ability>
					<time>517</time>
					<level>2</level>
				</ability>
				<ability>
					<ability>5190</ability>
					<time>581</time>
					<level>3</level>
				</ability>
				<ability>
					<ability>5191</ability>
					<time>649</time>
					<level>4</level>
				</ability>
				<ability>
					<ability>5190</ability>
					<time>747</time>
					<level>5</level>
				</ability>
				<ability>
					<ability>5193</ability>
					<time>895</time>
					<level>6</level>
				</ability>
				<ability>
					<ability>5190</ability>
					<time>1106</time>
					<level>7</level>
				</ability>
				<ability>
					<ability>5191</ability>
					<time>1202</time>
					<level>8</level>
				</ability>
				<ability>
					<ability>5191</ability>
					<time>1504</time>
					<level>9</level>
				</ability>
				<ability>
					<ability>5192</ability>
					<time>1576</time>
					<level>10</level>
				</ability>
				<ability>
					<ability>5193</ability>
					<time>1712</time>
					<level>11</level>
				</ability>
				<ability>
					<ability>5192</ability>
					<time>2022</time>
					<level>12</level>
				</ability>
				<ability>
					<ability>5192</ability>
					<time>2118</time>
					<level>13</level>
				</ability>
				<ability>
					<ability>5192</ability>
					<time>2139</time>
					<level>14</level>
				</ability>
			</ability_upgrades>
		</player>
		<player>
			<account_id>167714776</account_id>
			<player_slot>129</player_slot>
			<hero_id>51</hero_id>
			<item_0>0</item_0>
			<item_1>0</item_1>
			<item_2>0</item_2>
			<item_3>0</item_3>
			<item_4>0</item_4>
			<item_5>102</item_5>
			<kills>0</kills>
			<deaths>7</deaths>
			<assists>3</assists>
			<leaver_status>0</leaver_status>
			<gold>166</gold>
			<last_hits>41</last_hits>
			<denies>2</denies>
			<gold_per_min>173</gold_per_min>
			<xp_per_min>95</xp_per_min>
			<gold_spent>5965</gold_spent>
			<hero_damage>4832</hero_damage>
			<tower_damage>0</tower_damage>
			<hero_healing>0</hero_healing>
			<level>7</level>
			<ability_upgrades>
				<ability>
					<ability>5239</ability>
					<time>383</time>
					<level>1</level>
				</ability>
				<ability>
					<ability>5237</ability>
					<time>494</time>
					<level>2</level>
				</ability>
				<ability>
					<ability>5238</ability>
					<time>586</time>
					<level>3</level>
				</ability>
				<ability>
					<ability>5239</ability>
					<time>670</time>
					<level>4</level>
				</ability>
				<ability>
					<ability>5237</ability>
					<time>924</time>
					<level>5</level>
				</ability>
				<ability>
					<ability>5240</ability>
					<time>1179</time>
					<level>6</level>
				</ability>
				<ability>
					<ability>5239</ability>
					<time>1624</time>
					<level>7</level>
				</ability>
			</ability_upgrades>
		</player>
		<player>
			<account_id>122474871</account_id>
			<player_slot>130</player_slot>
			<hero_id>32</hero_id>
			<item_0>63</item_0>
			<item_1>22</item_1>
			<item_2>46</item_2>
			<item_3>44</item_3>
			<item_4>0</item_4>
			<item_5>174</item_5>
			<kills>1</kills>
			<deaths>6</deaths>
			<assists>4</assists>
			<leaver_status>0</leaver_status>
			<gold>61</gold>
			<last_hits>31</last_hits>
			<denies>5</denies>
			<gold_per_min>239</gold_per_min>
			<xp_per_min>362</xp_per_min>
			<gold_spent>6575</gold_spent>
			<hero_damage>2576</hero_damage>
			<tower_damage>0</tower_damage>
			<hero_healing>0</hero_healing>
			<level>14</level>
			<ability_upgrades>
				<ability>
					<ability>5145</ability>
					<time>328</time>
					<level>1</level>
				</ability>
				<ability>
					<ability>5144</ability>
					<time>506</time>
					<level>2</level>
				</ability>
				<ability>
					<ability>5145</ability>
					<time>628</time>
					<level>3</level>
				</ability>
				<ability>
					<ability>5142</ability>
					<time>718</time>
					<level>4</level>
				</ability>
				<ability>
					<ability>5145</ability>
					<time>871</time>
					<level>5</level>
				</ability>
				<ability>
					<ability>5143</ability>
					<time>1026</time>
					<level>6</level>
				</ability>
				<ability>
					<ability>5145</ability>
					<time>1051</time>
					<level>7</level>
				</ability>
				<ability>
					<ability>5142</ability>
					<time>1162</time>
					<level>8</level>
				</ability>
				<ability>
					<ability>5142</ability>
					<time>1293</time>
					<level>9</level>
				</ability>
				<ability>
					<ability>5142</ability>
					<time>1562</time>
					<level>10</level>
				</ability>
				<ability>
					<ability>5143</ability>
					<time>1573</time>
					<level>11</level>
				</ability>
				<ability>
					<ability>5144</ability>
					<time>1738</time>
					<level>12</level>
				</ability>
				<ability>
					<ability>5144</ability>
					<time>1814</time>
					<level>13</level>
				</ability>
			</ability_upgrades>
		</player>
		<player>
			<account_id>4294967295</account_id>
			<player_slot>131</player_slot>
			<hero_id>86</hero_id>
			<item_0>102</item_0>
			<item_1>36</item_1>
			<item_2>188</item_2>
			<item_3>29</item_3>
			<item_4>46</item_4>
			<item_5>0</item_5>
			<kills>0</kills>
			<deaths>3</deaths>
			<assists>1</assists>
			<leaver_status>0</leaver_status>
			<gold>451</gold>
			<last_hits>30</last_hits>
			<denies>0</denies>
			<gold_per_min>165</gold_per_min>
			<xp_per_min>151</xp_per_min>
			<gold_spent>4660</gold_spent>
			<hero_damage>2367</hero_damage>
			<tower_damage>0</tower_damage>
			<hero_healing>0</hero_healing>
			<level>8</level>
			<ability_upgrades>
				<ability>
					<ability>5448</ability>
					<time>416</time>
					<level>1</level>
				</ability>
				<ability>
					<ability>5450</ability>
					<time>523</time>
					<level>2</level>
				</ability>
				<ability>
					<ability>5450</ability>
					<time>595</time>
					<level>3</level>
				</ability>
				<ability>
					<ability>5448</ability>
					<time>833</time>
					<level>4</level>
				</ability>
				<ability>
					<ability>5450</ability>
					<time>1053</time>
					<level>5</level>
				</ability>
				<ability>
					<ability>5452</ability>
					<time>1185</time>
					<level>6</level>
				</ability>
				<ability>
					<ability>5450</ability>
					<time>1473</time>
					<level>7</level>
				</ability>
				<ability>
					<ability>5448</ability>
					<time>1739</time>
					<level>8</level>
				</ability>
			</ability_upgrades>
		</player>
		<player>
			<account_id>4294967295</account_id>
			<player_slot>132</player_slot>
			<hero_id>98</hero_id>
			<item_0>41</item_0>
			<item_1>34</item_1>
			<item_2>180</item_2>
			<item_3>60</item_3>
			<item_4>182</item_4>
			<item_5>0</item_5>
			<kills>4</kills>
			<deaths>10</deaths>
			<assists>3</assists>
			<leaver_status>0</leaver_status>
			<gold>953</gold>
			<last_hits>81</last_hits>
			<denies>3</denies>
			<gold_per_min>349</gold_per_min>
			<xp_per_min>390</xp_per_min>
			<gold_spent>6915</gold_spent>
			<hero_damage>11834</hero_damage>
			<tower_damage>0</tower_damage>
			<hero_healing>0</hero_healing>
			<level>14</level>
			<ability_upgrades>
				<ability>
					<ability>5524</ability>
					<time>335</time>
					<level>1</level>
				</ability>
				<ability>
					<ability>5526</ability>
					<time>496</time>
					<level>2</level>
				</ability>
				<ability>
					<ability>5524</ability>
					<time>524</time>
					<level>3</level>
				</ability>
				<ability>
					<ability>5525</ability>
					<time>605</time>
					<level>4</level>
				</ability>
				<ability>
					<ability>5524</ability>
					<time>670</time>
					<level>5</level>
				</ability>
				<ability>
					<ability>5527</ability>
					<time>844</time>
					<level>6</level>
				</ability>
				<ability>
					<ability>5525</ability>
					<time>1014</time>
					<level>7</level>
				</ability>
				<ability>
					<ability>5524</ability>
					<time>1052</time>
					<level>8</level>
				</ability>
				<ability>
					<ability>5525</ability>
					<time>1296</time>
					<level>9</level>
				</ability>
				<ability>
					<ability>5525</ability>
					<time>1430</time>
					<level>10</level>
				</ability>
				<ability>
					<ability>5527</ability>
					<time>1564</time>
					<level>11</level>
				</ability>
				<ability>
					<ability>5526</ability>
					<time>1831</time>
					<level>12</level>
				</ability>
				<ability>
					<ability>5526</ability>
					<time>2017</time>
					<level>13</level>
				</ability>
				<ability>
					<ability>5526</ability>
					<time>2136</time>
					<level>14</level>
				</ability>
			</ability_upgrades>
		</player>
	</players>
	<radiant_win>true</radiant_win>
	<duration>1736</duration>
	<start_time>1416118843</start_time>
	<match_id>1028731837</match_id>
	<match_seq_num>920935273</match_seq_num>
	<tower_status_radiant>2047</tower_status_radiant>
	<tower_status_dire>0</tower_status_dire>
	<barracks_status_radiant>63</barracks_status_radiant>
	<barracks_status_dire>0</barracks_status_dire>
	<cluster>223</cluster>
	<first_blood_time>72</first_blood_time>
	<lobby_type>7</lobby_type>
	<human_players>10</human_players>
	<leagueid>0</leagueid>
	<positive_votes>1</positive_votes>
	<negative_votes>0</negative_votes>
	<game_mode>22</game_mode>
</result>